drawio2pptx/__init__.py
drawio2pptx/analysis.py
drawio2pptx/config.py
drawio2pptx/fonts.py
drawio2pptx/logger.py
drawio2pptx/main.py
drawio2pptx/geom/__init__.py
drawio2pptx/geom/transform.py
drawio2pptx/geom/units.py
drawio2pptx/io/__init__.py
drawio2pptx/io/drawio_loader.py
drawio2pptx/io/pptx_writer.py
drawio2pptx/mapping/__init__.py
drawio2pptx/mapping/shape_map.py
drawio2pptx/mapping/style_map.py
drawio2pptx/mapping/text_map.py
drawio2pptx/media/__init__.py
drawio2pptx/media/image_utils.py
drawio2pptx/model/__init__.py
drawio2pptx/model/intermediate.py
drawio2pptx-0.0.4.dist-info/licenses/LICENSE
drawio2pptx-0.0.4.dist-info/METADATA
drawio2pptx-0.0.4.dist-info/WHEEL
drawio2pptx-0.0.4.dist-info/entry_points.txt
drawio2pptx-0.0.4.dist-info/top_level.txt
drawio2pptx-0.0.4.dist-info/RECORD
