Metadata-Version: 2.4
Name: drawio2pptx
Version: 0.0.4
Summary: Convert draw.io (diagrams.net) files to PowerPoint (.pptx) format - mxGraph to PresentationML converter
Author: mashu3
License: MIT
Project-URL: Homepage, https://github.com/mashu3/drawio2pptx
Project-URL: Repository, https://github.com/mashu3/drawio2pptx
Project-URL: Issues, https://github.com/mashu3/drawio2pptx/issues
Keywords: drawio,diagrams.net,powerpoint,pptx,converter,mxgraph,presentationml
Classifier: Development Status :: 3 - Alpha
Classifier: Intended Audience :: Developers
Classifier: License :: OSI Approved :: MIT License
Classifier: Programming Language :: Python :: 3
Classifier: Programming Language :: Python :: 3.8
Classifier: Programming Language :: Python :: 3.9
Classifier: Programming Language :: Python :: 3.10
Classifier: Programming Language :: Python :: 3.11
Classifier: Programming Language :: Python :: 3.12
Classifier: Programming Language :: Python :: 3.13
Requires-Python: >=3.8
License-File: LICENSE
Requires-Dist: python-pptx>=0.6.21
Requires-Dist: lxml>=4.6.0
Provides-Extra: dev
Requires-Dist: pytest>=7.0.0; extra == "dev"
Requires-Dist: pytest-cov>=4.0.0; extra == "dev"
Requires-Dist: coverage>=7.0.0; extra == "dev"
Dynamic: license-file
